Population_15countries.py
Population_15countries-0.0.1.dist-info/METADATA
Population_15countries-0.0.1.dist-info/WHEEL
Population_15countries-0.0.1.dist-info/entry_points.txt
Population_15countries-0.0.1.dist-info/top_level.txt
Population_15countries-0.0.1.dist-info/RECORD
