Metadata-Version: 2.1
Name: Population-15countries
Version: 0.0.1
Summary: Output a graph of population densities in 15 populous countries
Home-page: https://github.com/MiyuIwamoto/Population_15countries
Author: miyu iwamoto
Author-email: s2022006@stu.musashino-u.ac.jp
License: UNKNOWN
Project-URL: Bug Tracker, https://github.com/MiyuIwamoto/Population_15countries
Platform: UNKNOWN
Classifier: Programming Language :: Python :: 3
Classifier: License :: OSI Approved :: MIT License
Classifier: Operating System :: OS Independent
Requires-Python: >=3.7
